sqvid/__init__.py
sqvid/console.py
sqvid/executor.py
sqvid/validators.py
sqvid-0.1.10.dist-info/entry_points.txt
sqvid-0.1.10.dist-info/LICENSE
sqvid-0.1.10.dist-info/WHEEL
sqvid-0.1.10.dist-info/METADATA
sqvid-0.1.10.dist-info/RECORD
