Metadata-Version: 2.1
Name: sqvid
Version: 0.1.10
Summary: SQVID: Simple sQl Validator of varIous Datasources
Home-page: https://github.com/mrshu/sqvid
License: Apache-2.0
Keywords: SQL,data,validation,test
Author: Marek Suppa
Author-email: mr@shu.io
Requires-Python: >=3.6,<4.0
Classifier: Development Status :: 3 - Alpha
Classifier: Environment :: Console
Classifier: Intended Audience :: Developers
Classifier: License :: OSI Approved :: Apache Software License
Classifier: Programming Language :: Python :: 3
Classifier: Programming Language :: Python :: 3.6
Classifier: Programming Language :: Python :: 3.7
Requires-Dist: click (>=8.0,<9.0)
Requires-Dist: envtoml (>=0.1.1,<0.2.0)
Requires-Dist: jinjasql (>=0.1.7,<0.2.0)
Requires-Dist: nicetable (>=0.7.0,<0.8.0)
Requires-Dist: sqlalchemy (>=1.3,<2.0)
Project-URL: Repository, https://github.com/mrshu/sqvid
